unsupcc/__init__.py
unsupcc/executer.py
unsupcc/classification/__init__.py
unsupcc/classification/crop_classifier.py
unsupcc/satellite/__init__.py
unsupcc/satellite/indices.py
unsupcc/satellite/sentinel2.py
unsupcc/satellite/satellite_tiles/s2_tile.dbf
unsupcc/satellite/satellite_tiles/s2_tile.prj
unsupcc/satellite/satellite_tiles/s2_tile.qpj
unsupcc/satellite/satellite_tiles/s2_tile.shp
unsupcc/satellite/satellite_tiles/s2_tile.shx
unsupcc/utils/__init__.py
unsupcc/utils/helper.py
unsupcc/utils/raster.py
crop_classifier-0.1.9.dist-info/LICENSE
crop_classifier-0.1.9.dist-info/METADATA
crop_classifier-0.1.9.dist-info/WHEEL
crop_classifier-0.1.9.dist-info/top_level.txt
crop_classifier-0.1.9.dist-info/RECORD
