Metadata-Version: 2.1
Name: crop-classifier
Version: 0.1.9
Summary: Unsupervised Crop Classification using Micro-spectral satellite imagery
Home-page: https://github.com/Dehaat/crop-classification
Author: Sumit Maan
Author-email: sumitmaansingh@gmail.com
License: GPLv3+
Keywords: GIS,GDAL,Remote Sensing,satellite,sentinel2,crop,crops
Requires-Python: >=3
License-File: LICENSE
